main.py
smartwheel/__init__.py
smartwheel/__main__.py
smartwheel/actionengine.py
smartwheel/canvas.py
smartwheel/common.py
smartwheel/config.py
smartwheel/gui_tools.py
smartwheel/launch.json
smartwheel/logo.png
smartwheel/settings.py
smartwheel/status.json
smartwheel/tools.py
smartwheel/actions/__init__.py
smartwheel/actions/baseaction.py
smartwheel/actions/custom.py
smartwheel/actions/keypress.py
smartwheel/actions/wheel/__init__.py
smartwheel/actions/wheel/base.py
smartwheel/actions/wheel/module.py
smartwheel/actions/wheel/wheel.py
smartwheel/api/__init__.py
smartwheel/api/action.py
smartwheel/api/app.py
smartwheel/api/settings.py
smartwheel/backgrounds/__init__.py
smartwheel/backgrounds/base.py
smartwheel/backgrounds/basic.py
smartwheel/backgrounds/config.json
smartwheel/backgrounds/config_defaults.json
smartwheel/backgrounds/contour.py
smartwheel/defaults/actionengine.json
smartwheel/defaults/common.json
smartwheel/defaults/config.json
smartwheel/defaults/folder.json
smartwheel/defaults/hue.json
smartwheel/defaults/media.json
smartwheel/defaults/midi.json
smartwheel/defaults/wheel.json
smartwheel/defaults/backgrounds/contour.json
smartwheel/defaults/backgrounds/pattern.json
smartwheel/defaults/internal/krita_server.json
smartwheel/defaults/serial/bgkeyboard.json
smartwheel/defaults/serial/keyboard.json
smartwheel/defaults/serial/serial.json
smartwheel/docs/conf.py
smartwheel/icons/default/folder.png
smartwheel/icons/default/hue.svg
smartwheel/icons/default/hue_old.png
smartwheel/icons/default/media.png
smartwheel/icons/default/pause.png
smartwheel/icons/default/play.png
smartwheel/icons/default/round.png
smartwheel/icons/ionicons/close.svg
smartwheel/icons/ionicons/disc.svg
smartwheel/icons/ionicons/folder.svg
smartwheel/icons/ionicons/hue.svg
smartwheel/icons/ionicons/media.svg
smartwheel/icons/ionicons/pause.svg
smartwheel/icons/ionicons/play.svg
smartwheel/icons/ionicons/settings.svg
smartwheel/icons/settings/add-outline.png
smartwheel_core-0.0.6.dist-info/LICENSE
smartwheel_core-0.0.6.dist-info/METADATA
smartwheel_core-0.0.6.dist-info/WHEEL
smartwheel_core-0.0.6.dist-info/entry_points.txt
smartwheel_core-0.0.6.dist-info/top_level.txt
smartwheel_core-0.0.6.dist-info/RECORD
