Metadata-Version: 2.1
Name: smartwheel-core
Version: 0.0.6
Summary: Keyboard knob/dial controller with a ton of features
Author-email: enaix <enaix@protonmail.com>
License: GNU GENERAL PUBLIC LICENSE
Project-URL: Homepage, https://github.com/enaix/smartwheel-core
Project-URL: Documentation, https://smartwheel-core.readthedocs.io/en/latest/
Keywords: gui,keyboard,knob
Classifier: Programming Language :: Python :: 3
Classifier: Operating System :: OS Independent
Classifier: License :: OSI Approved :: GNU General Public License v3 or later (GPLv3+)
License-File: LICENSE
Requires-Dist: pyserial
Requires-Dist: pynput
Requires-Dist: pyqt6
Requires-Dist: python-rtmidi
Requires-Dist: pyqtdarktheme
Requires-Dist: swcolorpicker
Requires-Dist: matplotlib
Requires-Dist: winsdk ; platform_system == "Windows"
Provides-Extra: dev
Requires-Dist: black ; extra == 'dev'
Requires-Dist: isort ; extra == 'dev'
Requires-Dist: numpydoc ; extra == 'dev'
